[
  {
    "@context": [
      "https://www.w3.org/2022/wot/td/v1.1",
      {
        "dov": "http://azure.com/DigitalOperations/vocab#"
      }
    ],
    "@type": "tm:ThingModel",
    "title": "AMLBaseTypes_CAEXBasicObjectType",
    "dov:typeRef": "org.opcfoundation.UA.AML.CAEXBasicObjectType",
    "dov:isComposite": true,
    "links": [
      {
        "rel": "tm:extends",
        "href": "./OpcUaCore.TM.json#title=OpcUaCore_BaseObjectType",
        "type": "application/tm+json"
      }
    ],
    "schemaDefinitions": {
    },
    "forms": [
      {
        "contentType": "application/json",
        "dov:topic": "opcua/AMLBaseTypes/AMLBaseTypes_CAEXBasicObjectType/properties/read",
        "op": "readallproperties"
      }
    ],
    "actions": {
    },
    "properties": {
      "Version": {
        "dov:namespace": "http://opcfoundation.org/UA/AML/",
        "type": "string",
        "readOnly": true,
        "forms": [
          {
            "contentType": "application/json",
            "dov:topic": "opcua/AMLBaseTypes/AMLBaseTypes_CAEXBasicObjectType/property/Version/read",
            "op": "readproperty"
          }
        ]
      }
    },
    "events": {
    }
  },
  {
    "@context": [
      "https://www.w3.org/2022/wot/td/v1.1",
      {
        "dov": "http://azure.com/DigitalOperations/vocab#"
      }
    ],
    "@type": "tm:ThingModel",
    "title": "AMLBaseTypes_CAEXFileType",
    "dov:typeRef": "org.opcfoundation.UA.AML.CAEXFileType",
    "dov:isComposite": true,
    "links": [
      {
        "rel": "tm:extends",
        "href": "#title=AMLBaseTypes_CAEXBasicObjectType",
        "type": "application/tm+json"
      },
      {
        "rel": "dov:component",
        "dov:refName": "InstanceHierarchies",
        "href": "./OpcUaCore.TM.json#title=OpcUaCore_FolderType",
        "type": "application/tm+json"
      },
      {
        "rel": "dov:component",
        "dov:refName": "InterfaceClassLibs",
        "href": "./OpcUaCore.TM.json#title=OpcUaCore_FolderType",
        "type": "application/tm+json"
      },
      {
        "rel": "dov:component",
        "dov:refName": "RoleClassLibs",
        "href": "./OpcUaCore.TM.json#title=OpcUaCore_FolderType",
        "type": "application/tm+json"
      },
      {
        "rel": "dov:component",
        "dov:refName": "SystemUnitClassLibs",
        "href": "./OpcUaCore.TM.json#title=OpcUaCore_FolderType",
        "type": "application/tm+json"
      }
    ],
    "schemaDefinitions": {
    },
    "actions": {
    },
    "properties": {
    },
    "events": {
    }
  },
  {
    "@context": [
      "https://www.w3.org/2022/wot/td/v1.1",
      {
        "dov": "http://azure.com/DigitalOperations/vocab#"
      }
    ],
    "@type": "tm:ThingModel",
    "title": "AMLBaseTypes_CAEXObjectType",
    "dov:typeRef": "org.opcfoundation.UA.AML.CAEXObjectType",
    "dov:isComposite": true,
    "links": [
      {
        "rel": "tm:extends",
        "href": "#title=AMLBaseTypes_CAEXBasicObjectType",
        "type": "application/tm+json"
      }
    ],
    "schemaDefinitions": {
    },
    "forms": [
      {
        "contentType": "application/json",
        "dov:topic": "opcua/AMLBaseTypes/AMLBaseTypes_CAEXObjectType/properties/read",
        "op": "readallproperties"
      }
    ],
    "actions": {
    },
    "properties": {
      "ID": {
        "dov:namespace": "http://opcfoundation.org/UA/AML/",
        "type": "string",
        "readOnly": true,
        "forms": [
          {
            "contentType": "application/json",
            "dov:topic": "opcua/AMLBaseTypes/AMLBaseTypes_CAEXObjectType/property/ID/read",
            "op": "readproperty"
          }
        ]
      }
    },
    "events": {
    }
  },
  {
    "@context": [
      "https://www.w3.org/2022/wot/td/v1.1",
      {
        "dov": "http://azure.com/DigitalOperations/vocab#"
      }
    ],
    "@type": "tm:ThingModel",
    "title": "AMLBaseTypes_AutomationMLBaseInterface",
    "dov:typeRef": "org.opcfoundation.UA.AML.AutomationMLBaseInterface",
    "dov:isComposite": true,
    "links": [
      {
        "rel": "tm:extends",
        "href": "#title=AMLBaseTypes_CAEXObjectType",
        "type": "application/tm+json"
      }
    ],
    "schemaDefinitions": {
    },
    "actions": {
    },
    "properties": {
    },
    "events": {
    }
  },
  {
    "@context": [
      "https://www.w3.org/2022/wot/td/v1.1",
      {
        "dov": "http://azure.com/DigitalOperations/vocab#"
      }
    ],
    "@type": "tm:ThingModel",
    "title": "AMLBaseTypes_AutomationMLBaseRole",
    "dov:typeRef": "org.opcfoundation.UA.AML.AutomationMLBaseRole",
    "dov:isComposite": true,
    "links": [
      {
        "rel": "tm:extends",
        "href": "#title=AMLBaseTypes_CAEXObjectType",
        "type": "application/tm+json"
      }
    ],
    "schemaDefinitions": {
    },
    "actions": {
    },
    "properties": {
    },
    "events": {
    }
  },
  {
    "@context": [
      "https://www.w3.org/2022/wot/td/v1.1",
      {
        "dov": "http://azure.com/DigitalOperations/vocab#"
      }
    ],
    "@type": "tm:ThingModel",
    "title": "AMLBaseTypes_AutomationMLBaseSystemUnit",
    "dov:typeRef": "org.opcfoundation.UA.AML.AutomationMLBaseSystemUnit",
    "dov:isComposite": true,
    "links": [
      {
        "rel": "tm:extends",
        "href": "#title=AMLBaseTypes_CAEXObjectType",
        "type": "application/tm+json"
      }
    ],
    "schemaDefinitions": {
    },
    "actions": {
    },
    "properties": {
    },
    "events": {
    }
  }
]
