[
  {
    "@context": [
      "https://www.w3.org/2022/wot/td/v1.1",
      {
        "dtv": "http://azure.com/DigitalTwins/dtmi#",
        "aov": "http://azure.com/IoT/operations/tm#"
      }
    ],
    "@type": "tm:ThingModel",
    "title": "Sercos_FunctionalGroupType",
    "aov:typeRef": "nsu=http://sercos.org/UA/;i=6012",
    "links": [
      {
        "rel": "tm:extends",
        "href": "./OpcUaCore.TM.json#title=OpcUaCore_FolderType",
        "type": "application/tm+json"
      }
    ],
    "schemaDefinitions": {
    },
    "actions": {
    },
    "properties": {
    },
    "events": {
    }
  },
  {
    "@context": [
      "https://www.w3.org/2022/wot/td/v1.1",
      {
        "dtv": "http://azure.com/DigitalTwins/dtmi#",
        "aov": "http://azure.com/IoT/operations/tm#"
      }
    ],
    "@type": "tm:ThingModel",
    "title": "Sercos_SercosProfileType",
    "aov:typeRef": "nsu=http://sercos.org/UA/;i=1002",
    "links": [
      {
        "rel": "tm:extends",
        "href": "#title=Sercos_FunctionalGroupType",
        "type": "application/tm+json"
      }
    ],
    "schemaDefinitions": {
    },
    "actions": {
    },
    "properties": {
    },
    "events": {
    }
  },
  {
    "@context": [
      "https://www.w3.org/2022/wot/td/v1.1",
      {
        "dtv": "http://azure.com/DigitalTwins/dtmi#",
        "aov": "http://azure.com/IoT/operations/tm#"
      }
    ],
    "@type": "tm:ThingModel",
    "title": "Sercos_SercosClassType",
    "aov:typeRef": "nsu=http://sercos.org/UA/;i=1003",
    "links": [
      {
        "rel": "tm:extends",
        "href": "#title=Sercos_FunctionalGroupType",
        "type": "application/tm+json"
      }
    ],
    "schemaDefinitions": {
    },
    "actions": {
    },
    "properties": {
    },
    "events": {
    }
  },
  {
    "@context": [
      "https://www.w3.org/2022/wot/td/v1.1",
      {
        "dtv": "http://azure.com/DigitalTwins/dtmi#",
        "aov": "http://azure.com/IoT/operations/tm#"
      }
    ],
    "@type": "tm:ThingModel",
    "title": "Sercos_SercosFunctionGroupType",
    "aov:typeRef": "nsu=http://sercos.org/UA/;i=1004",
    "links": [
      {
        "rel": "tm:extends",
        "href": "#title=Sercos_FunctionalGroupType",
        "type": "application/tm+json"
      }
    ],
    "schemaDefinitions": {
    },
    "actions": {
    },
    "properties": {
    },
    "events": {
    }
  },
  {
    "@context": [
      "https://www.w3.org/2022/wot/td/v1.1",
      {
        "dtv": "http://azure.com/DigitalTwins/dtmi#",
        "aov": "http://azure.com/IoT/operations/tm#"
      }
    ],
    "@type": "tm:ThingModel",
    "title": "Sercos_SercosDeviceType",
    "aov:typeRef": "nsu=http://sercos.org/UA/;i=1001",
    "aov:isComposite": true,
    "links": [
      {
        "rel": "tm:extends",
        "href": "./DI.TM.json#title=DI_DeviceType",
        "type": "application/tm+json"
      },
      {
        "rel": "aov:capability",
        "aov:refName": "ParameterSet",
        "href": "#title=Sercos_FunctionalGroupType",
        "type": "application/tm+json"
      },
      {
        "rel": "aov:capability",
        "aov:refName": "ProfileSet",
        "href": "#title=Sercos_FunctionalGroupType",
        "type": "application/tm+json"
      },
      {
        "rel": "aov:capability",
        "aov:refName": "ClassSet",
        "href": "#title=Sercos_FunctionalGroupType",
        "type": "application/tm+json"
      },
      {
        "rel": "aov:capability",
        "aov:refName": "FunctionGroupSet",
        "href": "#title=Sercos_FunctionalGroupType",
        "type": "application/tm+json"
      }
    ],
    "schemaDefinitions": {
    },
    "actions": {
    },
    "properties": {
    },
    "events": {
    }
  },
  {
    "@context": [
      "https://www.w3.org/2022/wot/td/v1.1",
      {
        "dtv": "http://azure.com/DigitalTwins/dtmi#",
        "aov": "http://azure.com/IoT/operations/tm#"
      }
    ],
    "@type": "tm:ThingModel",
    "title": "Sercos_ProfileSet",
    "aov:typeRef": "nsu=http://sercos.org/UA/;i=6075",
    "aov:isComposite": true,
    "links": [
      {
        "rel": "tm:extends",
        "href": "#title=Sercos_FunctionalGroupType",
        "type": "application/tm+json"
      },
      {
        "rel": "aov:component",
        "aov:refName": "SercosProfileIdentifier_Placeholder",
        "href": "#title=Sercos_SercosProfileType",
        "type": "application/tm+json"
      }
    ],
    "schemaDefinitions": {
    },
    "actions": {
    },
    "properties": {
    },
    "events": {
    }
  },
  {
    "@context": [
      "https://www.w3.org/2022/wot/td/v1.1",
      {
        "dtv": "http://azure.com/DigitalTwins/dtmi#",
        "aov": "http://azure.com/IoT/operations/tm#"
      }
    ],
    "@type": "tm:ThingModel",
    "title": "Sercos_ClassSet",
    "aov:typeRef": "nsu=http://sercos.org/UA/;i=6077",
    "aov:isComposite": true,
    "links": [
      {
        "rel": "tm:extends",
        "href": "#title=Sercos_FunctionalGroupType",
        "type": "application/tm+json"
      },
      {
        "rel": "aov:component",
        "aov:refName": "SercosClassIdentifier_Placeholder",
        "href": "#title=Sercos_SercosClassType",
        "type": "application/tm+json"
      }
    ],
    "schemaDefinitions": {
    },
    "actions": {
    },
    "properties": {
    },
    "events": {
    }
  },
  {
    "@context": [
      "https://www.w3.org/2022/wot/td/v1.1",
      {
        "dtv": "http://azure.com/DigitalTwins/dtmi#",
        "aov": "http://azure.com/IoT/operations/tm#"
      }
    ],
    "@type": "tm:ThingModel",
    "title": "Sercos_FunctionGroupSet",
    "aov:typeRef": "nsu=http://sercos.org/UA/;i=6079",
    "aov:isComposite": true,
    "links": [
      {
        "rel": "tm:extends",
        "href": "#title=Sercos_FunctionalGroupType",
        "type": "application/tm+json"
      },
      {
        "rel": "aov:component",
        "aov:refName": "FunctionGroupIdentifier_Placeholder",
        "href": "#title=Sercos_SercosFunctionGroupType",
        "type": "application/tm+json"
      }
    ],
    "schemaDefinitions": {
    },
    "actions": {
    },
    "properties": {
    },
    "events": {
    }
  }
]
